Workbook

Sheet categoría
A1: id | B1: Categoría
A2: 1 | B2: Lácteos
A3: 2 | B3: Cereales
A4: 3 | B4: Bebidas alcohólicas
A5: 4 | B5: Bebidas gaseosas
A6: 5 | B6: Encurtidos
A7: 6 | B7: Embutidos cárnicos
A8: 8 | B8: Legumbre
A9: 9 | B9: Bebidas

Sheet producto
A1: Id | B1: Código de barras | C1: Nombre del producto | D1: Marca | E1: Categoría | F1: Cantidad | G1: Unidad de medida | H1: Unidad agrupada | I1: Precio de venta | J1: Existencias | K1: Existencias mínimas
A2: 1 | B2: 78545454 | C2: Fréjol | D2: Su despensa | E2: 1 | F2: 10 | G2: kg | H2: NULL | I2: 1350 | J2: 15 | K2: 10
A3: =A2+1 -> 2 | B3: 78545455 | C3: Alverja | D3: Su despensa | E3: 2 | F3: 20 | G3: lb | H3: NULL | I3: 2000 | J3: 15 | K3: 20
A4: =A3+1 -> 3 | B4: 78545456 | C4: Arroz | D4: Boluga | E4: 8 | F4: 500 | G4: gr | H4: NULL | I4: 200 | J4: 24 | K4: 50
A5: =A4+1 -> 4 | B5: 78545457 | C5: Arroz x 24 | D5: Boluga | E5: 8 | F5: 24 | G5: NULL | H5: Arroz Boluga | I5: 5000 | J5: 11 | K5: 50
A6: =A5+1 -> 5 | B6: 78545458 | C6: Arroz | D6: Diana | F6: 1 | G6: @ | H6: NULL | I6: 2500 | J6: 26 | K6: 50
A7: =A6+1 -> 6 | B7: 78545459 | C7: Leche | D7: Gran Vía | E7: 9 | F7: 1 | G7: L | H7: NULL | I7: 4500 | J7: 4
A8: =A7+1 -> 7 | B8: 78545460 | C8: Yogur | D8: Alpina | F8: 1 | G8: L | H8: NULL | I8: 8500 | J8: 2
A9: =A8+1 -> 8 | B9: 78545461 | C9: Leche | D9: Alquería | F9: 1000 | G9: ml | H9: NULL | I9: 4000 | J9: 3
A10: =A9+1 -> 9 | B10: 78545462 | C10: Leche * 6 | D10: Alquería | E10: 4 | F10: 6 | G10: NULL | H10: 8 | I10: 13500 | J10: 5
A11: =A10+1 -> 10 | B11: 78545463 | C11: Leche * 12 | D11: Alquería | E11: 8 | F11: 12 | G11: NULL | H11: 8 | I11: 26000 | J11: 4
A12: =A11+1 -> 11 | B12: 78545464 | C12: Cerveza | D12: Poker | F12: 250 | G12: ml | H12: NULL | I12: 3000
A13: =A12+1 -> 12 | B13: 78545465 | C13: Cerveza Six Pack | D13: Poker | F13: 6 | G13: NULL | H13: 11 | I13: 25000
A14: =A13+1 -> 13 | B14: 78545466 | C14: Cerveza Bandeja | D14: Poker | F14: 24 | G14: NULL | H14: 11 | I14: 75000
A15: =A14+1 -> 14 | B15: 78545467 | C15: Leche * 6 | D15: Gran Vía | F15: 6 | G15: NULL | H15: 6 | I15: 20000
A16: =A15+1 -> 15 | B16: 78545468 | C16: Gaseosa negra | D16: Cocacola | F16: 250 | G16: ml | H16: NULL | I16: 4000
A17: =A16+1 -> 16 | B17: 78545469 | C17: Gaseosa negra | D17: Pepesi | F17: 250 | G17: ml | H17: NULL | I17: 6000
A18: =A17+1 -> 17 | B18: 78545470 | C18: Gaseosa uva | D18: Postobon | F18: 250 | G18: ml | H18: NULL | I18: 70000
A19: =A18+1 -> 18 | B19: 78545471 | C19: Chocolatina | D19: Jet | F19: 50 | G19: gr | H19: NULL | I19: 12000
A20: =A19+1 -> 19 | B20: 78545472 | C20: Corte costilla de res | F20: 1 | G20: lb | H20: NULL | I20: 18000

Sheet lote
A1: Id | B1: Id de producto | C1: Lote | D1: Fecha de registro | E1: Fecha de expedición | F1: Fecha de vencimiento | G1: Cantidad de inventario movido | H1: Valor monetario del Movimiento de inventario | I1: Motivo del movimento De invetario
A2: 1 | B2: =producto!A2 -> 1 | C2: =RANDBETWEEN(999,9999) -> 6105 | D2: 46219 | F2: 46433 | G2: 20 | H2: -100000 | I2: Compra
A3: =A2+1 -> 2 | B3: 1 | C3: =RANDBETWEEN(999,9999) -> 3269 | D3: 46220 | F3: 46428 | G3: 20 | H3: -1400
A4: =A3+1 -> 3 | B4: =producto!A4 -> 3 | C4: =RANDBETWEEN(999,9999) -> 5188 | D4: 46221 | F4: 46435 | G4: 10 | H4: -200
A5: =A4+1 -> 4 | B5: =producto!A5 -> 4 | C5: =RANDBETWEEN(999,9999) -> 2763 | D5: 46222 | F5: 46436 | G5: 5 | H5: -5000
A6: =A5+1 -> 5 | B6: =producto!A6 -> 5 | C6: =RANDBETWEEN(999,9999) -> 6205 | D6: 46223 | F6: 46437 | G6: 12 | H6: -2500
A7: =A6+1 -> 6 | B7: =producto!A7 -> 6 | C7: =RANDBETWEEN(999,9999) -> 1378 | D7: 46224 | F7: 46438 | G7: 10 | H7: -4500
A8: =A7+1 -> 7 | B8: =producto!A7 -> 6 | C8: =RANDBETWEEN(999,9999) -> 9259 | D8: 46225 | F8: 46439 | G8: 10 | H8: -8500
A9: =A8+1 -> 8 | B9: =producto!A9 -> 8 | C9: =RANDBETWEEN(999,9999) -> 2689 | D9: 46226 | F9: 46440 | G9: 30 | H9: -4000
A10: =A9+1 -> 9 | B10: =producto!A10 -> 9 | C10: =RANDBETWEEN(999,9999) -> 4706 | D10: 46227 | F10: 46441 | G10: 14 | H10: -13500
A11: =A10+1 -> 10 | B11: =producto!A12 -> 11 | C11: =RANDBETWEEN(999,9999) -> 5581 | D11: 46228 | F11: 46442 | G11: 54 | H11: -26000
A12: =A11+1 -> 11 | B12: =producto!A12 -> 11 | C12: =RANDBETWEEN(999,9999) -> 9485 | D12: 46229 | F12: 46443 | G12: 10 | H12: -3000
A13: =A12+1 -> 12 | B13: =producto!A13 -> 12 | C13: =RANDBETWEEN(999,9999) -> 5711 | D13: 46230 | F13: 46444 | G13: 30 | H13: -25000
A14: =A13+1 -> 13 | B14: =producto!A14 -> 13 | C14: =RANDBETWEEN(999,9999) -> 1744 | D14: 46231 | F14: 46445 | G14: 15 | H14: -75000
A15: =A14+1 -> 14 | B15: =producto!A15 -> 14 | C15: =RANDBETWEEN(999,9999) -> 8302 | D15: 46232 | F15: 46446 | G15: 5 | H15: -13000 | I15: Vencimiento
A16: =A15+1 -> 15 | B16: =producto!A2 -> 1 | C16: =RANDBETWEEN(999,9999) -> 5198 | D16: 46233 | F16: 46082 | G16: 5
A17: =A16+1 -> 16 | B17: =producto!A18 -> 17 | C17: =RANDBETWEEN(999,9999) -> 1734 | D17: 46234 | F17: 46448 | G17: 5
A18: =A17+1 -> 17 | B18: =producto!A18 -> 17 | C18: =RANDBETWEEN(999,9999) -> 4047 | D18: 46235 | F18: 46449 | G18: 5
A19: =A18+1 -> 18 | B19: =producto!A19 -> 18 | C19: =RANDBETWEEN(999,9999) -> 6839 | D19: 46236 | F19: 46450 | G19: 6 | H19: 10
A20: =A19+1 -> 19 | B20: =producto!A20 -> 19 | C20: =RANDBETWEEN(999,9999) -> 5663 | D20: 46237 | F20: 46247 | G20: 20 | H20: 15000
A21: =A20+1 -> 20 | B21: 1 | C21: =C3 -> 3269 | D21: 46220 | F21: 46428 | G21: -2 | H21: =H3/G3*G21 -> 140 | I21: Venta
A22: =A21+1 -> 21 | B22: 1 | C22: =C3 -> 3269 | D22: 46220 | F22: 46428 | G22: -6 | H22: -3000 | I22: Perdida

Sheet ventas
A1: Id | B1: Id cliente | C1: total | D1: fecha | E1: hora | F1: Pago
A2: 1 | B2: 1 | C2: 50000 | D2: 46023 | E2: 0.25 | F2: Credito de la tienda
A3: =A2+1 -> 2 | B3: NULL | F3: Efectivo
A4: 3 | B4: 2 | C4: 70000 | F4: Credito de la tienda
F5: Transferencia
F6: Datafono

Sheet detalle de la venta
A1: Id de venta | B1: Id de producto | C1: Cantidad | D1: Valor Individual
A2: 1 | B2: 1 | C2: 2
A3: 1 | B3: 4 | C3: 5
A4: 1 | B4: 3 | C4: 7
A5: 1 | B5: 2 | C5: 1
A6: 2 | B6: 1 | C6: 6
A7: 3 | B7: 2 | C7: 1 | D7: 1400
A8: 3 | B8: 1 | C8: 1
A9: 3 | B9: 11 | C9: 1
A10: 3 | B10: 19 | C10: 5

Sheet cliente
A1: Id | B1: Nombre | C1: Cedula | D1: Correo | E1: Telefono | F1: Saldo
A2: 1 | B2: Jose Prada | C2: 10000000 | D2: jp@email.com | E2: 3552277777 | F2: 70000
A3: =A2+1 -> 2 | B3: Taxi Pedro | C3: 12555555 | D3: tp@email.com | E3: 3225448454 | F3: 55000

Sheet alertas
A1: titulo | B1: cuerpo | C1: En la RAM
A2: Agotado
A3: Vencimineto
