Workbook

Sheet producto
A1: Id | B1: Codigo de barras | C1: Nombre del producto | D1: Marca | E1: Cantidad | F1: Unidad de medida | G1: Unidad agrupaga | H1: Precio de venta | I1: Existencias
A2: 1 | B2: 78545454 | C2: Fréjol | D2: Su despensa | E2: 10 | F2: kg | G2: NULL | H2: 1350 | I2: 15
A3: =A2+1 -> 2 | B3: 78545455 | C3: Alverja | D3: Su despensa | E3: 20 | F3: lb | G3: NULL | H3: 2000 | I3: 15
A4: =A3+1 -> 3 | B4: 78545456 | C4: Arroz | D4: Boluga | E4: =30*500 -> 15000 | F4: gr | G4: NULL | H4: 200 | I4: 14
A5: =A4+1 -> 4 | B5: 78545457 | C5: Arroz | D5: Diana | E5: 1 | F5: kg | G5: NULL | H5: 5000 | I5: 12
A6: =A5+1 -> 5 | B6: 78545458 | C6: Arroz | D6: Diana | E6: 1 | F6: @ | G6: NULL | H6: 2500 | I6: 26
A7: =A6+1 -> 6 | B7: 78545459 | C7: Leche | D7: Gran Vía | E7: 1 | F7: L | G7: NULL | H7: 4500 | I7: 4
A8: =A7+1 -> 7 | B8: 78545460 | C8: Yogur | D8: Alpina | E8: 1 | F8: L | G8: NULL | H8: 8500 | I8: 2
A9: =A8+1 -> 8 | B9: 78545461 | C9: Leche | D9: Alquería | E9: 1000 | F9: ml | G9: NULL | H9: 4000
A10: =A9+1 -> 9 | B10: 78545462 | C10: Leche * 6 | D10: Alquería | E10: 6 | F10: NULL | G10: 8 | H10: 13500
A11: =A10+1 -> 10 | B11: 78545463 | C11: Leche * 12 | D11: Alquería | E11: 12 | F11: NULL | G11: 8 | H11: 26000
A12: =A11+1 -> 11 | B12: 78545464 | C12: Cerveza | D12: Poker | E12: 250 | F12: ml | G12: NULL | H12: 3000
A13: =A12+1 -> 12 | B13: 78545465 | C13: Cerveza Six Pack | D13: Poker | E13: 6 | F13: NULL | G13: 11 | H13: 25000
A14: =A13+1 -> 13 | B14: 78545466 | C14: Cerveza Bandeja | D14: Poker | E14: 24 | F14: NULL | G14: 11 | H14: 75000
A15: =A14+1 -> 14 | B15: 78545467 | C15: Leche * 6 | D15: Gran Vía | E15: 6 | F15: NULL | G15: 6 | H15: 20000
A16: =A15+1 -> 15 | B16: 78545468 | C16: Gaseosa negra | D16: Cocacola | E16: 250 | F16: ml | G16: NULL | H16: 4000
A17: =A16+1 -> 16 | B17: 78545469 | C17: Gaseosa negra | D17: Pepesi | E17: 250 | F17: ml | G17: NULL | H17: 6000
A18: =A17+1 -> 17 | B18: 78545470 | C18: Gaseosa uva | D18: Postobon | E18: 250 | F18: ml | G18: NULL | H18: 70000
A19: =A18+1 -> 18 | B19: 78545471 | C19: Chocolatina | D19: Jet | E19: 50 | F19: gr | G19: NULL | H19: 12000
A20: =A19+1 -> 19 | B20: 78545472 | C20: Corte costilla de res | E20: 1 | F20: lb | G20: NULL | H20: 18000

Sheet historico de productos
A1: Id | B1: Id de producto | C1: Lote | D1: Fecha registro | E1: Fecha de vencimiento | F1: Cantidad | G1: Precio total compra
A2: 1 | B2: =producto!A2 -> 1 | C2: =RANDBETWEEN(999,9999) -> 5208 | D2: 46219 | E2: 46433 | F2: 20 | G2: 100000
A3: =A2+1 -> 2 | B3: 1 | C3: =RANDBETWEEN(999,9999) -> 3803 | D3: 46220 | E3: 46428 | F3: 20 | G3: 1400
A4: =A3+1 -> 3 | B4: =producto!A4 -> 3 | C4: =RANDBETWEEN(999,9999) -> 9994 | D4: 46221 | E4: 46435 | F4: 10 | G4: 200
A5: =A4+1 -> 4 | B5: =producto!A5 -> 4 | C5: =RANDBETWEEN(999,9999) -> 4641 | D5: 46222 | E5: 46436 | F5: 5 | G5: 5000
A6: =A5+1 -> 5 | B6: =producto!A6 -> 5 | C6: =RANDBETWEEN(999,9999) -> 2774 | D6: 46223 | E6: 46437 | F6: 12 | G6: 2500
A7: =A6+1 -> 6 | B7: =producto!A7 -> 6 | C7: =RANDBETWEEN(999,9999) -> 7757 | D7: 46224 | E7: 46438 | F7: 10 | G7: 4500
A8: =A7+1 -> 7 | B8: =producto!A7 -> 6 | C8: =RANDBETWEEN(999,9999) -> 9099 | D8: 46225 | E8: 46439 | F8: 10 | G8: 8500
A9: =A8+1 -> 8 | B9: =producto!A9 -> 8 | C9: =RANDBETWEEN(999,9999) -> 4686 | D9: 46226 | E9: 46440 | F9: 30 | G9: 4000
A10: =A9+1 -> 9 | B10: =producto!A10 -> 9 | C10: =RANDBETWEEN(999,9999) -> 2757 | D10: 46227 | E10: 46441 | F10: 14 | G10: 13500
A11: =A10+1 -> 10 | B11: =producto!A12 -> 11 | C11: =RANDBETWEEN(999,9999) -> 3038 | D11: 46228 | E11: 46442 | F11: 54 | G11: 26000
A12: =A11+1 -> 11 | B12: =producto!A12 -> 11 | C12: =RANDBETWEEN(999,9999) -> 9553 | D12: 46229 | E12: 46443 | F12: 10 | G12: 3000
A13: =A12+1 -> 12 | B13: =producto!A13 -> 12 | C13: =RANDBETWEEN(999,9999) -> 3148 | D13: 46230 | E13: 46444 | F13: 30 | G13: 25000
A14: =A13+1 -> 13 | B14: =producto!A14 -> 13 | C14: =RANDBETWEEN(999,9999) -> 5716 | D14: 46231 | E14: 46445 | F14: 15 | G14: 75000
A15: =A14+1 -> 14 | B15: =producto!A15 -> 14 | C15: =RANDBETWEEN(999,9999) -> 3352 | D15: 46232 | E15: 46446 | F15: 5 | G15: 13000
A16: =A15+1 -> 15 | B16: =producto!A2 -> 1 | C16: =RANDBETWEEN(999,9999) -> 3682 | D16: 46233 | E16: 46082 | F16: 5
A17: =A16+1 -> 16 | B17: =producto!A18 -> 17 | C17: =RANDBETWEEN(999,9999) -> 1425 | D17: 46234 | E17: 46448 | F17: 5
A18: =A17+1 -> 17 | B18: =producto!A18 -> 17 | C18: =RANDBETWEEN(999,9999) -> 1705 | D18: 46235 | E18: 46449 | F18: 5
A19: =A18+1 -> 18 | B19: =producto!A19 -> 18 | C19: =RANDBETWEEN(999,9999) -> 7333 | D19: 46236 | E19: 46450 | F19: 6
A20: =A19+1 -> 19 | B20: =producto!A20 -> 19 | C20: =RANDBETWEEN(999,9999) -> 4778 | D20: 46237 | E20: 46247 | F20: 20 | G20: 15000
A21: =A20+1 -> 20 | B21: 1 | C21: =C3 -> 3803 | D21: 46220 | E21: 46428 | F21: -2 | G21: -3000

Sheet hitorico de ventas
A1: Id | B1: Id cliente | C1: total | D1: fecha | E1: hora | F1: Pago
A2: 1 | B2: 1 | C2: 50000 | D2: 46023 | E2: 0.25 | F2: Credito de la tienda
A3: =A2+1 -> 2 | B3: NULL | F3: Efectivo
A4: 3 | B4: 2 | C4: 70000 | F4: Credito de la tienda
F5: Transferencia
F6: Datafono

Sheet detalle de la venta
A1: Id de venta | B1: Id de producto | C1: Cantidad | D1: Valor Individual
A2: 1 | B2: 1 | C2: 2
A3: 1 | B3: 4 | C3: 5
A4: 1 | B4: 3 | C4: 7
A5: 1 | B5: 2 | C5: 1
A6: 2
A7: 3 | B7: 2 | C7: 1 | D7: 1400
A8: 3 | B8: 1 | C8: 1
A9: 3 | B9: 11 | C9: 1
A10: 3 | B10: 19 | C10: 5

Sheet cliente
A1: Id | B1: Nombre | C1: Cedula | D1: Correo | E1: Telefono | F1: Saldo
A2: 1 | B2: Jose Prada | C2: 10000000 | D2: jp@email.com | E2: 3552277777 | F2: 70000
A3: =A2+1 -> 2 | B3: Taxi Pedro | C3: 12555555 | D3: tp@email.com | E3: 3225448454 | F3: 55000

Sheet historico credito
A1: Id | B1: Id Cliente | C1: Id Venta | D1: Credito | E1: Pago
A2: 1 | B2: 3 | C2: 3 | D2: -70000 | E2: Credito de la tienda
A3: =A2+1 -> 2 | E3: Efectivo
A4: 3 | B4: 3 | C4: 3 | D4: 15000 | E4: Efectivo
E5: Transferencia
E6: Datafono
